<?xml version="1.0" encoding="UTF-8" ?>
<!--
	 This file is part of xmlbandplan.

    Xmlbandplan is free software: you can redistribute it and/or modify
    it under the terms of the GNU General Public License as published by
    the Free Software Foundation, either version 3 of the License, or
    (at your option) any later version.

    Xmlbandplan is distributed in the hope that it will be useful,
    but WITHOUT ANY WARRANTY; without even the implied warranty of
    MERCHANTABILITY or FITNESS FOR A PARTICULAR PURPOSE.  See the
    GNU General Public License for more details.

    You should have received a copy of the GNU General Public License
    along with Xmlbandplan.  If not, see <http://www.gnu.org/licenses/>.	  
-->

<!-- 

	  Follow the two letter ISO 3166 code (http://en.wikipedia.org/wiki/ISO_3166-1) 

-->

<!DOCTYPE note SYSTEM "bandplan.dtd">

<bandplan version="0.7.12">

<countries>
	<country name="AL" fullname="Albania">
		<license name="CEPT" cept="CEPT" prefix="ZA" ref="TR6101"/>
	</country>

	<country name="AT" fullname="Austria">
		<license name="1" cept="CEPT" prefix="OE" ref="TR6101"/>
	</country>

	<country name="BE" fullname="Belgium">
		<license name="A" cept="CEPT" prefix="ON" ref="TR6101"/>
	</country>

	<country name="BA" fullname="Bosnia and Herzegovina">
		<license name="CEPT 1" cept="CEPT" prefix="E7" ref="TR6101"/>
	</country>

	<country name="BG" fullname="Bulgaria">
		<license name="Class 1" cept="CEPT" prefix="LZ" ref="TR6101"/>
	</country>

	<country name="HR" fullname="Croatia">
		<license name="CEPT" cept="CEPT" prefix="9A" ref="TR6101"/>
	</country>

	<country name="CY" fullname="Cyprus">
		<license name="Radioamateur Authorisation" cept="CEPT" prefix="5B" ref="TR6101"/>
	</country>

	<country name="CZ" fullname="Czech Republic">
		<license name="A" cept="CEPT" prefix="OK" ref="TR6101"/>
	</country>

	<country name="DK" fullname="Denmark">
		<license name="A" cept="CEPT" prefix="OZ" ref="TR6101"/>
		<country name="FO" fullname="Faroe Islands">
			<license name="A" cept="CEPT" prefix="OY" ref="TR6101"/>
		</country>
		<country name="GL" fullname="Greenland">
			<license name="A" cept="CEPT" prefix="OX" ref="TR6101"/>
		</country>
	</country>

	<country name="EE" fullname="Estonia">
		<license name="A" cept="CEPT" prefix="ES" ref="TR6101"/>
		<license name="B" cept="CEPT" prefix="ES" ref="TR6101"/>
	</country>

	<country name="FI" fullname="Finnland">
		<license name="L" cept="CEPT" prefix="OH" ref="TR6101"/>
		<license name="P" cept="CEPT" prefix="OH" ref="TR6101"/>
		<license name="T" cept="CEPT" prefix="OH" ref="TR6101"/>
		<license name="Y" cept="CEPT" prefix="OH" ref="TR6101"/>
		<country name="AX" fullname="Aland Islands">
			<license name="L" cept="CEPT" prefix="OH0" ref="TR6101"/>
			<license name="P" cept="CEPT" prefix="OH0" ref="TR6101"/>
			<license name="T" cept="CEPT" prefix="OH0" ref="TR6101"/>
			<license name="Y" cept="CEPT" prefix="OH0" ref="TR6101"/>
		</country>
	</country>

	<country name="FR" fullname="France">
		<license name="1" cept="CEPT" prefix="F" ref="TR6101"/>
		<license name="2" cept="CEPT" prefix="F" ref="TR6101"/>
		<country name="FR" fullname="Corsica">
			<license name="1" cept="CEPT" prefix="TK" ref="TR6101"/>
			<license name="2" cept="CEPT" prefix="TK" ref="TR6101"/>
		</country>
		<country name="GP" fullname="Guadeloupe">
			<license name="1" cept="CEPT" prefix="FG" ref="TR6101"/>
			<license name="2" cept="CEPT" prefix="FG" ref="TR6101"/>
		</country>
		<country name="GY" fullname="Guyana">
			<license name="1" cept="CEPT" prefix="FY" ref="TR6101"/>
			<license name="2" cept="CEPT" prefix="FY" ref="TR6101"/>
		</country>
		<country name="MQ" fullname="Martinique">
			<license name="1" cept="CEPT" prefix="FM" ref="TR6101"/>
			<license name="2" cept="CEPT" prefix="FM" ref="TR6101"/>
		</country>
		<country name="BL" fullname="St-Bartholomew">
			<license name="1" cept="CEPT" prefix="FJ" ref="TR6101"/>
			<license name="2" cept="CEPT" prefix="FJ" ref="TR6101"/>
		</country>
		<country name="PM" fullname="St-Pierre/Miquelon">
			<license name="1" cept="CEPT" prefix="FP" ref="TR6101"/>
			<license name="2" cept="CEPT" prefix="FP" ref="TR6101"/>
		</country>
		<country name="MF" fullname="St-Martin">
			<license name="1" cept="CEPT" prefix="FS" ref="TR6101"/>
			<license name="2" cept="CEPT" prefix="FS" ref="TR6101"/>
		</country>
		<country name="FR" fullname="Reunion (Glorieure, Jean de Nova, Tromelin)">
			<license name="1" cept="CEPT" prefix="FR" ref="TR6101"/>
			<license name="2" cept="CEPT" prefix="FR" ref="TR6101"/>
		</country>
		<country name="YT" fullname="Mayotte">
			<license name="1" cept="CEPT" prefix="FH" ref="TR6101"/>
			<license name="2" cept="CEPT" prefix="FH" ref="TR6101"/>
		</country>
		<country name="FR" fullname="French Antarctica (Crozet, Kerguelen, St. Paul and Amsterdam, Terre Adelie">
			<license name="1" cept="CEPT" prefix="FT" ref="TR6101"/>
			<license name="2" cept="CEPT" prefix="FT" ref="TR6101"/>
		</country>
		<country name="FR" fullname="French Polynesia and Clipperton">
			<license name="1" cept="CEPT" prefix="FO" ref="TR6101"/>
			<license name="2" cept="CEPT" prefix="FO" ref="TR6101"/>
		</country>
		<country name="NC" fullname="New Caledonia">
			<license name="1" cept="CEPT" prefix="FK" ref="TR6101"/>
			<license name="2" cept="CEPT" prefix="FK" ref="TR6101"/>
		</country>
		<country name="WF" fullname="Wallis and Futuna">
			<license name="1" cept="CEPT" prefix="FW" ref="TR6101"/>
			<license name="2" cept="CEPT" prefix="FW" ref="TR6101"/>
		</country>
	</country>

	<country name="DE" fullname="Germany">
		<license name="Klasse_A" cept="CEPT" prefix="DL" ref="TR6101"/>
		<license name="Klasse_E" cept="CEPT-Novice" prefix="DO" ref="REC0506"/>
		<license name="PMR" prefix="" ref="DEPMR01"/>
		<license name="LPD" prefix="" ref="DELPD01"><comment>New name is SRD short rande devices</comment></license>
	</country>

	<country name="GR" fullname="Greece">
		<license name="1" cept="CEPT" prefix="SV" ref="TR6101"/>
	</country>

	<country name="HU" fullname="Hungary">
		<license name="CEPT" cept="CEPT" prefix="HA" ref="TR6101"/>
		<license name="CEPT" cept="CEPT" prefix="HG" ref="TR6101"/>
	</country>

	<country name="IS" fullname="Iceland">
		<license name="G" cept="CEPT" prefix="TF" ref="TR6101"/>
	</country>

	<country name="IE" fullname="Ireland">
		<license name="CEPT 1" cept="CEPT" prefix="EI" ref="TR6101"/>
		<license name="CEPT 2" cept="CEPT" prefix="EJ" ref="TR6101"/>
	</country>

	<country name="IT" fullname="Italy">
		<license name="General" cept="CEPT" prefix="I" ref="TR6101"/>
	</country>

	<country name="LV" fullname="Latvia">
		<license name="1" cept="CEPT" prefix="YL" ref="TR6101"/>
		<license name="2" cept="CEPT" prefix="YL" ref="TR6101"/>
	</country>

	<country name="LI" fullname="Liechtenstein">
		<license name="CEPT" cept="CEPT" prefix="HB0" ref="TR6101"/>
	</country>

	<country name="LT" fullname="Lithuania">
		<license name="A" cept="CEPT" prefix="LY" ref="TR6101"/>
	</country>

	<country name="LU" fullname="Louxembourgh">
		<license name="CEPT" cept="CEPT" prefix="LX" ref="TR6101"/>
	</country>

	<country name="MK" fullname="Macedonia (FYROM)">
		<license name="A" cept="CEPT" prefix="Z3" ref="TR6101"/>
		<license name="P" cept="CEPT" prefix="Z3" ref="TR6101"/>
	</country>

	<country name="MC" fullname="Monaco">
		<license name="General" cept="CEPT" prefix="3A" ref="TR6101"/>
	</country>

	<country name="ME" fullname="Montenegro">
		<license name="A" cept="CEPT" prefix="4O" ref="TR6101"/>
		<license name="N" cept="CEPT" prefix="4O" ref="TR6101"/>
	</country>

	<country name="NL" fullname="Netherlands">
		<license name="A" cept="CEPT" prefix="PA" ref="TR6101"/>
		<license name="C" cept="CEPT" prefix="PA" ref="TR6101"/>
		<license name="F" cept="CEPT" prefix="PA" ref="TR6101"/>
	</country>

	<country name="NO" fullname="Norway">
		<license name="A" cept="CEPT" prefix="LA" ref="TR6101"/>
		<country name="SJ" fullname="Svalbard">
			<license name="A" cept="CEPT" prefix="JW" ref="TR6101"/>
		</country>
	</country>

	<country name="PL" fullname="Poland">
		<license name="1" cept="CEPT" prefix="SP" ref="TR6101"/>
	</country>

	<country name="PT" fullname="Portugal">
		<license name="1" cept="CEPT" prefix="CT7" ref="TR6101"/>
		<license name="A" cept="CEPT" prefix="CT7" ref="TR6101"/>
		<license name="B" cept="CEPT" prefix="CT7" ref="TR6101"/>
		<country name="PT" fullname="Azores">
			<license name="1" cept="CEPT" prefix="CT8" ref="TR6101"/>
			<license name="A" cept="CEPT" prefix="CT8" ref="TR6101"/>
			<license name="B" cept="CEPT" prefix="CT8" ref="TR6101"/>
		</country>
		<country name="PT" fullname="Madeira">
			<license name="1" cept="CEPT" prefix="CT9" ref="TR6101"/>
			<license name="A" cept="CEPT" prefix="CT9" ref="TR6101"/>
			<license name="B" cept="CEPT" prefix="CT9" ref="TR6101"/>
		</country>
	</country>

	<country name="RO" fullname="Romania">
		<license name="I" cept="CEPT" prefix="YO" ref="TR6101"/>
		<license name="II" cept="CEPT" prefix="YO" ref="TR6101"/>
	</country>
	
	<country name="RU" fullname="Russian Federation">
		<license name="1" cept="CEPT" prefix="RA" ref="TR6101"/>
		<license name="2" cept="CEPT" prefix="RA" ref="TR6101"/>
	</country>

	<country name="RS" fullname="Serbia">
		<license name="1" cept="CEPT" prefix="YU" ref="TR6101"/>
	</country>

	<country name="SK" fullname="Slovak Republic">
		<license name="E" cept="CEPT" prefix="OM" ref="TR6101"/>
	</country>

	<country name="SI" fullname="Slovenia">
		<license name="A" cept="CEPT" prefix="S5" ref="TR6101"/>
	</country>

	<country name="ES" fullname="Spain">
		<license name="A" cept="CEPT" prefix="EA" ref="TR6101"/>
	</country>

	<country name="SE" fullname="Sweden">
		<license name="All" cept="CEPT" prefix="SM" ref="TR6101"/>
		<license name="All" cept="CEPT" prefix="SA" ref="TR6101"/>
	</country>

	<country name="CH" fullname="Switzerland">
		<license name="1" cept="CEPT" prefix="HB9" ref="TR6101"/>
		<license name="2" cept="CEPT" prefix="HB9" ref="TR6101"/>
		<license name="CEPT" cept="CEPT" prefix="HB9" ref="TR6101"/>
	</country>
	
	<country name="TR" fullname="Turkey">
		<license name="A" cept="CEPT" prefix="TA" ref="TR6101"/>
	</country>

	<country name="ZA" fullname="South Africa"/>

	<country name="UA" fullname="Ukraine">
		<license name="1" cept="CEPT" prefix="UT" ref="TR6101"/>
		<license name="2" cept="CEPT" prefix="UT" ref="TR6101"/>
	</country>

	<country name="GB" fullname="United Kingdom">
		<license name="FULL" cept="CEPT" prefix="M" ref="TR6101"/>
		<country name="IM" fullname="Isle of Man">
			<license name="FULL" cept="CEPT" prefix="MD" ref="TR6101"/>
		</country>
		<country name="IE" fullname="N. Ireland">
			<license name="FULL" cept="CEPT" prefix="MI" ref="TR6101"/>
		</country>
		<country name="JE" fullname="Jersey">
			<license name="FULL" cept="CEPT" prefix="MJ" ref="TR6101"/>
		</country>
		<country name="GB" fullname="Scotland">
			<license name="FULL" cept="CEPT" prefix="MM" ref="TR6101"/>
		</country>
		<country name="GG" fullname="Guernsey">
			<license name="FULL" cept="CEPT" prefix="MU" ref="TR6101"/>
		</country>
		<country name="GB" fullname="Wales">
			<license name="FULL" cept="CEPT" prefix="MW" ref="TR6101"/>
		</country>
	</country>



	<country name="US" fullname="USA">
		<license name="Amateur_Extra" prefix="" ref="US01"/>
		<license name="Advanced" prefix="" ref="US01"/>
		<license name="General" prefix="" ref="US01"/>
		<license name="Technician" prefix="" ref="US01"/>
		<license name="Novice" prefix="" ref="US01"/>
	</country>



	<country name="IARU1"/>
	<country name="IARU2"/>
	<country name="IARU3"/>

</countries>

</bandplan>
